pykazoo
