Metadata-Version: 1.0
Name: PyKazoo
Version: 0.0a7
Summary: PyKazoo is a Python API client for 2600hz Kazoo
Home-page: https://github.com/tnewman/PyKazoo
Author: Thomas Newman
Author-email: tnewman@users.noreply.github.com
License: MIT
Platform: UNKNOWN
